echor_logger/__init__.py
echor_logger/index.py
echor_logger/logError.py
echor_logger/logSuccess.py
echor_logger/util/__init__.py
echor_logger/util/formatTimestamp.py
echor_logger/util/getDateParams.py
echor_logger-0.2.2.dist-info/METADATA
echor_logger-0.2.2.dist-info/WHEEL
echor_logger-0.2.2.dist-info/top_level.txt
echor_logger-0.2.2.dist-info/RECORD
