Metadata-Version: 2.1
Name: echor-logger
Version: 0.2.2
Summary: A simple Python logging utility
Author: Pradeep
Classifier: Programming Language :: Python :: 3
Classifier: License :: OSI Approved :: MIT License
Classifier: Operating System :: OS Independent
Requires-Python: >=3.6
Requires-Dist: python-dotenv
